{
    "meta": {
        "lang": {
            "native": "ภาษาไทย",
            "english": "Thai"
        }
    },
    "common": {
        "settings": "การตั้งค่า",
        "back": "กลับ",
        "forward": "ส่งต่อ",
        "exit": "ออกจาก"
    },
    "start": {
        "camera": "ถ่ายภาพ",
        "photo_lib": "ไลบรารีรูปภาพ",
        "files": "เรียกดูไฟล์",
        "clipboard": "คลิปบอร์ด",
        "latest": "ใช้รูปถ่ายล่าสุด"
    },
    "main": {
        "manga": "มังงะ",
        "anime": "อะนิเมะ",
        "hentai": "เฮ็นไต",
        "h_anime": "เฮ็นไตอะนิเมะ",
        "artworks": "ภาพประกอบของอะนิเมะและเฮ็นไต",
        "cgs": "CG",
        "general": "ทั่วไป",
        "sep": ", ",
        "back_choose": "กลับไปที่เลือกภาพ",
        "choose_new": "เลือกรูปภาพใหม่",
        "unsupported": [
            "อินพุตที่ไม่รองรับ",
            "ไม่สามารถรับ URL หรือรูปภาพจากอินพุต ({{input_types}})\nต้องเป็น URL, ข้อความที่มี URL, รูปภาพหรือสื่อภาพถ่าย"
        ],
        "baidu_err": [
            "ข้อผิดพลาดการค้นหา",
            "ไป่ตู้กลับสถานะ {{status}}:"
        ],
        "baidu_404": [
            "การตอบสนองไม่ถูกต้อง",
            "ไป่ตู้คืนการตอบกลับที่ไม่ถูกต้อง\nดูเหมือนว่า URL นี้จะถูกบล็อกในประเทศจีน"
        ]
    },
    "settings": {
        "about": [
            "เกี่ยวกับ"
        ],
        "feedback": [
            "ผลตอบรับ",
            "เปิดหน้า RoutineHub"
        ],
        "update": [
            "ตรวจสอบสำหรับการอัพเดต",
            "ต้องใช้การเชื่อมต่อเครือข่าย"
        ],
        "customize": [
            "ปรับแต่ง",
            "แสดง / ซ่อนเครื่องมือค้นหา"
        ],
        "lang": [
            "ภาษา",
            "เปลี่ยนภาษา"
        ],
        "advanced": [
            "ตัวเลือกขั้นสูง"
        ]
    },
    "about": {
        "desc": "“{{what}}” ทำให้การค้นหาที่มาของภาพของคุณเป็นเรื่องง่าย",
        "made_by": "ทำโดย {{who}}",
        "wt_made_by": "{{what}} สร้างโดย {{who}}",
        "wt_creat_by": "{{what}} สร้างโดย {{who}}",
        "thank_you": "ขอขอบคุณ!"
    },
    "update": {
        "install": "ติดตั้งในขณะนี้",
        "whats_new": "มีอะไรใหม่ใน {{version}}",
        "changelog": "ประวัติบันทึกย่อประจำรุ่นทั้งหมด",
        "up_to_date": "รุ่นของคุณเป็นรุ่นล่าสุดแล้ว",
        "available": "มีการอัปเดต",
        "network": "ไม่สามารถตรวจสอบการอัปเดต\nโปรดตรวจสอบการเชื่อมต่อเครือข่ายของคุณแล้วลองอีกครั้ง",
        "server": "ไม่สามารถตรวจสอบการอัปเดต\nกรุณาลองใหม่อีกครั้งในภายหลัง.\n\nหากเกิดข้อผิดพลาดซ้ำ ๆ กันโปรดส่งข้อเสนอแนะให้ฉัน\nคุณสามารถตรวจสอบการตอบสนองของเซิร์ฟเวอร์ได้ที่ {{settings}} → {{debug}} → {{latest_response}}"
    },
    "advanced": {
        "enabled": "เปิดใช้งาน",
        "disabled": "ปิดการใช้งาน",
        "delete_imgur": [
            "ลบรูปภาพ Imgur เมื่อออก"
        ],
        "debug": [
            "ดีบัก"
        ]
    }
}
